progress0316/__init__.py
progress0316/bar.py
progress0316-0.1.2.dist-info/METADATA
progress0316-0.1.2.dist-info/WHEEL
progress0316-0.1.2.dist-info/top_level.txt
progress0316-0.1.2.dist-info/RECORD
