Metadata-Version: 2.1
Name: progress0316
Version: 0.1.2
Summary: Progress Bar
Home-page: UNKNOWN
Author: Friscobuffo
Author-email: <friscobuffo@gmail.com>
License: UNKNOWN
Keywords: python,progress,bar
Platform: UNKNOWN
Classifier: Development Status :: 1 - Planning
Classifier: Intended Audience :: Developers
Classifier: Programming Language :: Python :: 3
Classifier: Operating System :: Unix
Classifier: Operating System :: MacOS :: MacOS X
Classifier: Operating System :: Microsoft :: Windows
